xbow_validation_benchmarks_sdk/__init__.py
xbow_validation_benchmarks_sdk/managers/__init__.py
xbow_validation_benchmarks_sdk/managers/environment.py
xbow_validation_benchmarks_sdk/managers/repository.py
xbow_validation_benchmarks_sdk/models/__init__.py
xbow_validation_benchmarks_sdk/models/benchmark.py
xbow_validation_benchmarks_sdk/models/environment.py
xbow_validation_benchmarks_sdk-0.0.14.dist-info/METADATA
xbow_validation_benchmarks_sdk-0.0.14.dist-info/WHEEL
xbow_validation_benchmarks_sdk-0.0.14.dist-info/RECORD
