Metadata-Version: 2.4
Name: xbow-validation-benchmarks-sdk
Version: 0.0.14
Summary: Add your description here
Requires-Python: >=3.12
Requires-Dist: dotenv>=0.9.9
Requires-Dist: gitpython>=3.1.45
Requires-Dist: portpicker>=1.6.0
Requires-Dist: pydantic>=2.12.5
Requires-Dist: python-on-whales>=0.79.0
Requires-Dist: pyyaml>=6.0.3
Requires-Dist: rich>=14.2.0
Requires-Dist: structlog>=25.5.0
Requires-Dist: typer>=0.20.1
